LabExers/LE6/HexDigitCounter/HexTo7SegmentDecoder.v
// Chrys Sean T. Sevilla
// Group 4 CPE 3101L 10:30AM - 1:30PM
// Verilog HDL code for HexTo7SegmentDecoder

module HexTo7SegmentDecoder (
    input  [3:0] hex,       // 4-bit hexadecimal input
    input        dp,        // Decimal point control (active low)
    output reg [7:0] seg    // 7-segment output: seg[6:0] = segments a-g, seg[7] = DP
);

    always @(*) begin
        case (hex)
            
4'h0: seg[6:0] = 7'b0000001;
            4'h1: seg[6:0] = 7'b1001111;
            4'h2: seg[6:0] = 7'b0010010;
            4'h3: seg[6:0] = 7'b0000110;
            4'h4: seg[6:0] = 7'b1001100;
            4'h5: seg[6:0] = 7'b0100100;
            4'h6: seg[6:0] = 7'b0100000;
            4'h7: seg[6:0] = 7'b0001111;
            4'h8: seg[6:0] = 7'b0000000;
            4'h9: seg[6:0] = 7'b0000100;
            
				4'hA: seg[6:0] = 7'b0001000;
            4'hB: seg[6:0] = 7'b1100000;
            4'hC: seg[6:0] = 7'b0110001;
            4'hD: seg[6:0] = 7'b1000010;
            4'hE: seg[6:0] = 7'b0110000;
            4'hF: seg[6:0] = 7'b0111000;
            default: seg[6:0] = 7'b1111111; // All segments off
        endcase

        seg[7] = dp; // Decimal point (active low)
    end

endmodule

LabExers/LE6/HexDigitCounter/FourbitUpDownCounter.v
// Chrys Sean T. Sevilla
// Group 4 CPE 3101L 10:30AM - 1:30PM
// Verilog HDL code for FourbitUpDownCounter

module FourbitUpDownCounter (
    input wire clk,           // Clock input
    input wire reset,         // Active-low reset
    input wire load,          // Parallel load enable
    input wire count_en,      // Count enable
    input wire up,            // Direction: 1 = up, 0 = down
    input wire [3:0] data_in, // Parallel data input
    output reg [3:0] count    // Counter output
);

    always @(posedge clk or negedge reset) begin
        if (!reset)
            count <= 4'b0000; // Reset to 0
        else if (load)
            count <= data_in; // Load parallel input
        else if (count_en) begin
            if (up)
                count <= count + 4'd1; // Count up
            else
                count <= count - 4'd1; // Count down
        end
        // else: no change
    end

endmodule

LabExers/LE6/HexDigitCounter/ClockDivider.v
// Chrys Sean T. Sevilla
// Group 4 CPE 3101L 10:30AM - 1:30PM
// Verilog HDL code for ClockDivider

module ClockDivider (
    input wire clk_in,      // 50 MHz input clock
    input wire nReset,      // Active-low asynchronous reset
    output reg clk_out      // Divided clock output
);

    // Calculate division factor:
    // 50 MHz / 2 Hz = 25,000,000 cycles per half-period
    parameter DIV_FACTOR = 25_000_000; // For FPGA
    // For simulation, use smaller value like 10 or 20

    reg [24:0] counter; // Enough bits for 25 million

    always @(posedge clk_in or negedge nReset) begin
        if (!nReset) begin
            counter <= 0;
            clk_out <= 0;
        end else begin
            if (counter == DIV_FACTOR - 1) begin
                counter <= 0;
                clk_out <= ~clk_out; // Toggle output
            end else begin
                counter <= counter + 1;
            end
        end
    end

endmodule

LabExers/LE6/HexDigitCounter/HexDigitCounter.v
// Chrys Sean T. Sevilla
// Group 4 CPE 3101L 10:30AM - 1:30PM
// Verilog HDL code for HexDigitCounter

module HexDigitCounter (
    input wire clk_in,       // 50 MHz FPGA clock
    input wire nReset,       // Active-low reset
    input wire load,         // Load enable for counter
    input wire count_en,     // Count enable
    input wire up,           // Direction: 1 = up, 0 = down
    input wire [3:0] data_in,// Parallel load data
    input wire dp,           // Decimal point control
    output wire [7:0] seg   // 7-segment output (active low)
);

    wire slow_clk;           // Output from clock divider
    wire [3:0] count;        // Output from counter

    // Instantiate Clock Divider
    ClockDivider #(.DIV_FACTOR(12_500_000)) clk_div (
        .clk_in(clk_in),
        .nReset(nReset),
        .clk_out(slow_clk)
    );

    // Instantiate 4-bit Up/Down Counter
    FourbitUpDownCounter counter (
        .clk(slow_clk),
        .reset(nReset),
        .load(load),
        .count_en(count_en),
        .up(up),
        .data_in(data_in),
        .count(count)
    );

    // Instantiate Hex-to-7-Segment Decoder
    HexTo7SegmentDecoder decoder (
        .hex(count),
        .dp(dp),
        .seg(seg)
    );

endmodule

LabExers/LE6/HexDigitCounter/tb_HexDigitCounter.v
/*
File:           tb_HexDigitCounter.v
Author:         Chrys Sean T. Sevilla
Class:          CPE 3101L
Group/Schedule: Group 4 Fri 10:30 - 1:30 PM
Description:    Testbench for HexDigitCounter (1 up cycle, 1 down cycle)
*/

`timescale 1ns / 1ps

module tb_HexDigitCounter;

    reg clk_in, nReset, load, count_en, up, dp;
    reg [3:0] data_in;
    wire [7:0] seg;

    HexDigitCounter uut (
        .clk_in(clk_in),
        .nReset(nReset),
        .load(load),
        .count_en(count_en),
        .up(up),
        .data_in(data_in),
        .dp(dp),
        .seg(seg)
    );

    // Clock generation
    initial begin
        clk_in = 0;
        forever #1 clk_in = ~clk_in; // Fast clock for simulation
    end

    // Force slow_clk to bypass divider
    initial begin
        force uut.slow_clk = clk_in;
    end

    // Decode function for seg
    function [3:0] decode_seg;
        input [7:0] seg;
        begin
            case (seg)
                8'hC0: decode_seg = 4'h0;
                8'hF9: decode_seg = 4'h1;
                8'hA4: decode_seg = 4'h2;
                8'hB0: decode_seg = 4'h3;
                8'h99: decode_seg = 4'h4;
                8'h92: decode_seg = 4'h5;
                8'h82: decode_seg = 4'h6;
                8'hF8: decode_seg = 4'h7;
                8'h80: decode_seg = 4'h8;
                8'h90: decode_seg = 4'h9;
                8'h88: decode_seg = 4'hA;
                8'h83: decode_seg = 4'hB;
                8'hC6: decode_seg = 4'hC;
                8'hA1: decode_seg = 4'hD;
                8'h86: decode_seg = 4'hE;
                8'h8E: decode_seg = 4'hF;
                default: decode_seg = 4'hX;
            endcase
        end
    endfunction

    initial begin

        $display("Time\tReset\tLoad\tCountEn\tUp\tDataIn\tSeg\tDigit");
        $monitor("%0t\t%b\t%b\t%b\t%b\t%h\t%h\t%h", 
                  $time, nReset, load, count_en, up, data_in, seg, decode_seg(seg));

        // Initial reset
        nReset = 0; load = 0; count_en = 0; up = 1; dp = 1; data_in = 4'h0;
        #5 nReset = 1;

        // Load A
        load = 1; data_in = 4'hA; #10;
        load = 0;

        // Count up for 1 cycle
        count_en = 1; up = 1; #20;

        // Count down for 1 cycle
        up = 0; #20;

        // Stop simulation
        $stop;
    end

endmodule

LabExers/LE6/HexDigitCounter/simulation/modelsim/HexDigitCounter.vcd
$date
	Sat Nov 29 00:50:12 2025
$end
$version
	ModelSim Version 2020.1
$end
$timescale
	1ps
$end

$scope module tb_HexDigitCounter $end
$var reg 1 ! clk_in $end
$var reg 1 " nReset $end
$var reg 1 # load $end
$var reg 1 $ count_en $end
$var reg 1 % up $end
$var reg 1 & dp $end
$var reg 4 ' data_in [3:0] $end
$var wire 1 ( seg [7] $end
$var wire 1 ) seg [6] $end
$var wire 1 * seg [5] $end
$var wire 1 + seg [4] $end
$var wire 1 , seg [3] $end
$var wire 1 - seg [2] $end
$var wire 1 . seg [1] $end
$var wire 1 / seg [0] $end

$scope function decode_seg $end
$var reg 4 0 decode_seg [3:0] $end
$var reg 8 1 seg [7:0] $end
$upscope $end

$scope module uut $end
$var wire 1 2 clk_in $end
$var wire 1 3 nReset $end
$var wire 1 4 load $end
$var wire 1 5 count_en $end
$var wire 1 6 up $end
$var wire 1 7 data_in [3] $end
$var wire 1 8 data_in [2] $end
$var wire 1 9 data_in [1] $end
$var wire 1 : data_in [0] $end
$var wire 1 ; dp $end
$var wire 1 ( seg [7] $end
$var wire 1 ) seg [6] $end
$var wire 1 * seg [5] $end
$var wire 1 + seg [4] $end
$var wire 1 , seg [3] $end
$var wire 1 - seg [2] $end
$var wire 1 . seg [1] $end
$var wire 1 / seg [0] $end
$var wire 1 < slow_clk $end
$var wire 1 = count [3] $end
$var wire 1 > count [2] $end
$var wire 1 ? count [1] $end
$var wire 1 @ count [0] $end

$scope module clk_div $end
$var parameter 32 A DIV_FACTOR $end
$var wire 1 2 clk_in $end
$var wire 1 3 nReset $end
$var reg 1 B clk_out $end
$var reg 25 C counter [24:0] $end
$upscope $end

$scope module counter $end
$var wire 1 < clk $end
$var wire 1 3 reset $end
$var wire 1 4 load $end
$var wire 1 5 count_en $end
$var wire 1 6 up $end
$var wire 1 7 data_in [3] $end
$var wire 1 8 data_in [2] $end
$var wire 1 9 data_in [1] $end
$var wire 1 : data_in [0] $end
$var reg 4 D count [3:0] $end
$upscope $end

$scope module decoder $end
$var wire 1 = hex [3] $end
$var wire 1 > hex [2] $end
$var wire 1 ? hex [1] $end
$var wire 1 @ hex [0] $end
$var wire 1 ; dp $end
$var reg 8 E seg [7:0] $end
$upscope $end
$upscope $end
$upscope $end
$enddefinitions $end
#0
$dumpvars
0!
0"
0#
0$
1%
1&
b0 '
0B
b0 C
b0 D
b11000000 E
b0 0
b11000000 1
b101111101011110000100000 A
0/
0.
0-
0,
0+
0*
1)
1(
0<
0@
0?
0>
0=
1;
0:
09
08
07
16
05
04
03
02
$end
#1000
1!
12
1<
#2000
0!
02
0<
#3000
1!
12
1<
#4000
0!
02
0<
#5000
1"
1#
b1010 '
1!
14
19
17
13
12
1<
b1 C
b1010 D
1?
1=
b10001000 E
1,
0)
b10001000 1
b1010 0
#6000
0!
02
0<
#7000
1!
12
1<
b10 C
#8000
0!
02
0<
#9000
1!
12
1<
b11 C
#10000
0!
02
0<
#11000
1!
12
1<
b100 C
#12000
0!
02
0<
#13000
1!
12
1<
b101 C
#14000
0!
02
0<
#15000
0#
1$
1!
04
15
12
1<
b110 C
b1011 D
1@
b10000011 E
1/
1.
0,
b10000011 1
b1011 0
#16000
0!
02
0<
#17000
1!
12
1<
b111 C
b1100 D
0@
0?
1>
b11000110 E
0/
1-
1)
b11000110 1
b1100 0
#18000
0!
02
0<
#19000
1!
12
1<
b1000 C
b1101 D
1@
b10100001 E
1/
0.
0-
1*
0)
b10100001 1
b1101 0
#20000
0!
02
0<
#21000
1!
12
1<
b1001 C
b1110 D
0@
1?
b10000110 E
0/
1.
1-
0*
b10000110 1
b1110 0
#22000
0!
02
0<
#23000
1!
12
1<
b1010 C
b1111 D
1@
b10001110 E
1,
b10001110 1
b1111 0
#24000
0!
02
0<
#25000
1!
12
1<
b1011 C
b0 D
0@
0?
0>
0=
b11000000 E
0.
0-
0,
1)
b11000000 1
b0 0
#26000
0!
02
0<
#27000
1!
12
1<
b1100 C
b1 D
1@
b11111001 E
1/
1,
1+
1*
b11111001 1
b1 0
#28000
0!
02
0<
#29000
1!
12
1<
b1101 C
b10 D
0@
1?
b10100100 E
0/
1-
0,
0+
0)
b10100100 1
b10 0
#30000
0!
02
0<
#31000
1!
12
1<
b1110 C
b11 D
1@
b10110000 E
0-
1+
b10110000 1
b11 0
#32000
0!
02
0<
#33000
1!
12
1<
b1111 C
b100 D
0@
0?
1>
b10011001 E
1/
1,
0*
b10011001 1
b100 0
#34000
0!
02
0<
#35000
0%
1!
06
12
1<
b10000 C
b11 D
1@
1?
0>
b10110000 E
0/
0,
1*
b10110000 1
b11 0
#36000
0!
02
0<
#37000
1!
12
1<
b10001 C
b10 D
0@
b10100100 E
1-
0+
b10100100 1
b10 0
#38000
0!
02
0<
#39000
1!
12
1<
b10010 C
b1 D
1@
0?
b11111001 E
1/
0-
1,
1+
1)
b11111001 1
b1 0
#40000
0!
02
0<
#41000
1!
12
1<
b10011 C
b0 D
0@
b11000000 E
0/
0,
0+
0*
b11000000 1
b0 0
#42000
0!
02
0<
#43000
1!
12
1<
b10100 C
b1111 D
1@
1?
1>
1=
b10001110 E
1.
1-
1,
0)
b10001110 1
b1111 0
#44000
0!
02
0<
#45000
1!
12
1<
b10101 C
b1110 D
0@
b10000110 E
0,
b10000110 1
b1110 0
#46000
0!
02
0<
#47000
1!
12
1<
b10110 C
b1101 D
1@
0?
b10100001 E
1/
0.
0-
1*
b10100001 1
b1101 0
#48000
0!
02
0<
#49000
1!
12
1<
b10111 C
b1100 D
0@
b11000110 E
0/
1.
1-
0*
1)
b11000110 1
b1100 0
#50000
0!
02
0<
#51000
1!
12
1<
b11000 C
b1011 D
1@
1?
0>
b10000011 E
1/
0-
0)
b10000011 1
b1011 0
#52000
0!
02
0<
#53000
1!
12
1<
b11001 C
b1010 D
0@
b10001000 E
0/
0.
1,
b10001000 1
b1010 0
